hanifx_timelock/__init__.py
hanifx_timelock/timelock.py
hanifx_timelock-6.1.1.dist-info/METADATA
hanifx_timelock-6.1.1.dist-info/WHEEL
hanifx_timelock-6.1.1.dist-info/top_level.txt
hanifx_timelock-6.1.1.dist-info/RECORD
